{
    "Molkereifachmann": "Molkerei", 
    "Musiktherapeut": "Musiktherapie", 
    "Agrochemiker": "Agrochemie", 
    "Betonstein- und Terrazzohersteller": "Werksteinhersteller", 
    "Radio- und Fernsehtechniker": "Informationselektroniker", 
    "Hubschrauberf\u00fchrer": "Pilot", 
    "Kulturwirt": "Studiengang Kulturwirt", 
    "Schulleiter": "Schulleitung", 
    "Modedesigner": "Modedesign", 
    "Gie\u00dfer": "Gie\u00dfen (Verfahren)", 
    "Schmiedemeister": "Schmied", 
    "Neuropsychologe": "Neuropsychologie", 
    "Heilerziehungspflegehelfer": "Heilerziehungspflege", 
    "Geo\u00f6kologe": "Geo\u00f6kologie", 
    "Heilp\u00e4dagoge": "Heilp\u00e4dagogik", 
    "Telefonagent": "Callcenteragent", 
    "Szenenbildner": "Szenenbild", 
    "Ozeanograf": "Meereskunde", 
    "Ma\u00dfschuhmacher": "Schuh", 
    "Weintechnologe": "Weink\u00fcfer", 
    "Gestalter f\u00fcr visuelles Marketing": "Schauwerbegestalter", 
    "Rettungsdiensthelfer": "Rettungshelfer", 
    "Bauschlosser": "Metallbau", 
    "Posamentierer": "Posament", 
    "Hafenmeister": "Hafenkapit\u00e4n", 
    "Trickfilmzeichner": "Animation", 
    "Flugzeugmechaniker": "flugger\u00e4tmechaniker", 
    "Stahlbauer": "Stahlbau", 
    "Tibetologe": "Tibetologie", 
    "Verhaltenstherapeut": "Verhaltenstherapie", 
    "Finanzdienstleister": "Finanzdienstleistung", 
    "Prostituierter": "M\u00e4nnliche Prostitution", 
    "\u00c4gyptologe": "\u00c4gyptologie", 
    "Byzantinist": "Byzantinistik", 
    "Key-Account-Manager": "Key-Account-Management", 
    "Pferdepfleger": "Pferdewirt", 
    "Medi\u00e4vist": "Medi\u00e4vistik", 
    "Bergbauingenieur": "Montanwissenschaften", 
    "Geograf": "Geograph", 
    "Metallbauer": "Metallbau", 
    "Kernphysiker": "Kernphysik", 
    "Personalvermittler": "Personalvermittlung", 
    "Zoow\u00e4rter": "Tierpfleger", 
    "Indologe": "Indologie", 
    "Schnittmeister": "Cutter (Film)", 
    "Germanist": "Germanistik", 
    "Exportkaufmann": "Kaufmann im Gro\u00df- und Au\u00dfenhandel", 
    "Mineraloge": "Mineralogie", 
    "Ingenieur\u00f6konom": "Wirtschaftsingenieurwesen", 
    "Strumpfwirker": "Gewirke", 
    "Rechtlicher Betreuer": "Betreuer (Recht)", 
    "Kulturwissenschaftler": "Kulturwissenschaft", 
    "Netzwerkadministrator": "Systemadministrator", 
    "Metallurge": "Metallurgie", 
    "Fuger": "Martin Fuger", 
    "Musikerzieher": "Musikp\u00e4dagogik", 
    "Gesundheitsaufseher": "Hygienekontrolleur", 
    "Nautischer Schiffsoffizier": "Nautischer Offizier", 
    "Neogr\u00e4zist": "Neogr\u00e4zistik", 
    "Beikoch": "K\u00fcchenhilfe", 
    "Dekateur": "dekatieren", 
    "Wirtschaftsp\u00e4dagoge": "Wirtschaftsp\u00e4dagogik", 
    "T\u00f6pfer": "T\u00f6pferei", 
    "Katholischer Theologe": "Katholische Theologie", 
    "Regeltechniker": "Prozessleitelektroniker", 
    "Bautischler": "Tischler", 
    "Lehrtherapeut": "Lehrtherapie", 
    "Hom\u00f6opath": "Hom\u00f6opathie", 
    "Stellmacher": "Stellmacherei", 
    "Qualit\u00e4tsmanager": "Qualit\u00e4tsbeauftragter", 
    "Reprovorbereiter": "Reprovorbereitung", 
    "Kunsttischler": "Ebenist", 
    "Maschineningenieur": "Maschinenbauingenieur", 
    "Autolackierer": "Fahrzeuglackierer", 
    "Holzblasinstrumentenbauer": "Holzblasinstrumentenmacher", 
    "Arzthelfer": "Medizinischer Fachangestellter", 
    "Gro\u00dfhandelskaufmann": "Kaufmann im Gro\u00df- und Au\u00dfenhandel", 
    "Fliesen-, Platten- und Mosaikleger": "Fliesenleger", 
    "Bibliotheksassistent": "Fachangestellter f\u00fcr Medien- und Informationsdienste", 
    "\u00d6konom": "Wirtschaftswissenschaftler", 
    "Religionsp\u00e4dagoge": "Religionsp\u00e4dagogik", 
    "Dressman": "Model", 
    "Neurowissenschaftler": "Neurowissenschaften", 
    "Mongolist": "Mongolistik", 
    "Filmwissenschaftler": "Filmwissenschaft", 
    "Akrobat": "Akrobatik", 
    "Islamwissenschaftler": "Islamwissenschaft", 
    "Manufakturporzellanmaler": "Porzellanmaler", 
    "Assistenzzahnarzt": "Assistenzarzt", 
    "Siebdrucker": "Siebdruck", 
    "Stationsleiter": "Chief of Station", 
    "Musikredakteur": "Redakteur", 
    "Bekleidungsgestalter": "Ma\u00dfschneider", 
    "Account Manager": "Account-Manager", 
    "Romanist": "Romanistik", 
    "Intonateur": "Intonation (Musik)", 
    "Sprecherzieher": "Sprecherziehung", 
    "Vermessungsingenieur": "Geod\u00e4t", 
    "Schiffsf\u00fchrer": "Kapit\u00e4n", 
    "Berufsberater": "Berufsberatung", 
    "Fotografenmeister": "Fotograf", 
    "Krankenpflegehelfer": "Gesundheits- und Krankenpflegehelfer", 
    "Fachplaner": "Fachplanung", 
    "Saisonarbeiter": "Saisonarbeit", 
    "Schmucksteinfasser": "Edelsteinfasser", 
    "Gemeindehelfer": "Gemeindereferent", 
    "Pferdewirtschaftsmeister": "Pferdewirt", 
    "Formgestalter": "Designer", 
    "Informationswissenschaftler": "Informationswissenschaft", 
    "Taxifahrer": "Taxi", 
    "Praktikant": "Praktikum", 
    "Lademeister": "Verladung", 
    "Raumpfleger": "Reinigungskraft", 
    "Produktmanager": "Produktmanagement", 
    "Personalberater": "Personalberatung", 
    "Sportmanager": "Sportmanagement", 
    "Beifahrer": "Fahrer", 
    "Silberschmied": "Goldschmied", 
    "Betriebsleiter": "Betriebsleitung", 
    "Sozialarbeiter": "Soziale_Arbeit", 
    "Choreograf": "Choreografie", 
    "Pflegediensthelfer": "Schwesternhelferin", 
    "Genetiker": "Genetik", 
    "Schiffsjunge": "Seemann", 
    "Baubiologe": "Baubiologie", 
    "Konditor": "Konditorei", 
    "Wirtschaftsgeograf": "Wirtschaftsgeographie", 
    "Slawist": "Slawistik", 
    "Oberfl\u00e4chenbeschichter": "Galvaniseur", 
    "Bauingenieur": "Bauingenieurwesen", 
    "Gr\u00e4zist": "Gr\u00e4zistik", 
    "Kraftfahrzeugmechatroniker": "Kfz-Mechatroniker", 
    "Binnenschiffer": "Binnenschifffahrt", 
    "Amerikanist": "Amerikanistik", 
    "Sozial\u00f6konom": "Sozial\u00f6konomie", 
    "Musikschullehrer": "Musikschule", 
    "Hauswirtschaftshelfer": "Hauswirtschaft", 
    "Museumsp\u00e4dagoge": "Museumsp\u00e4dagogik", 
    "Testk\u00e4ufer": "Mystery Shopping", 
    "Statistiker": "Statistik", 
    "Epidemiologe": "Epidemiologie", 
    "Automatisierungstechniker": "Automatisierungstechnik", 
    "Backofenbauer": "Ofenbauer", 
    "Theatermaler": "B\u00fchnenmaler", 
    "Vollmatrose": "Seemann", 
    "Kristallograph": "Kristallographie", 
    "Bildender K\u00fcnstler": "Bildende Kunst", 
    "Sozialp\u00e4dagoge": "Diplom-Sozialp\u00e4dagoge", 
    "Verhaltensforscher": "Verhaltensbiologie", 
    "Ern\u00e4hrungsberater": "Ern\u00e4hrungsberatung", 
    "Museologe": "Museologie", 
    "Kontakter": "Werbeagentur", 
    "Schwei\u00dffachmann": "schwei\u00dfaufsicht", 
    "Au\u00dfendienstleiter": "Einsatzleiter", 
    "Fernmeldemonteur": "Fernmeldehandwerker", 
    "Golflehrer": "Berufsgolfer", 
    "Ofen- und Luftheizungsbauer": "Ofenbauer", 
    "Berufseinstiegsbegleiter": "Berufseinstiegsbegleitung", 
    "Touristikmanager": "Tourismusmanagement", 
    "Meteorologe": "Meteorologie", 
    "Puppenspieler": "Puppentheater", 
    "Gemeindepfleger": "K\u00e4mmerer", 
    "Auktionator": "Auktion", 
    "Nautiker": "Nautik", 
    "Gartenbautechniker": "G\u00e4rtner", 
    "Gesundheitswissenschaftler": "Gesundheitswissenschaften", 
    "Aus- und Weiterbildungsp\u00e4dagoge": "Gepr\u00fcfter Aus- und Weiterbildungsp\u00e4dagoge", 
    "Japanologe": "Japanologie", 
    "Musterzeichner": "Dessinateur", 
    "Bandagist": "Orthop\u00e4dietechnik-Mechaniker", 
    "Chemieverfahrenstechniker": "Chemikant", 
    "Betriebsschlosser": "Schlosserei", 
    "K\u00e4lteanlagenbauer": "Mechatroniker f\u00fcr K\u00e4ltetechnik", 
    "Glasbildner": "Netzwerkbildner", 
    "Sch\u00e4fer": "Sch\u00e4ferei", 
    "Mediendesigner": "Mediendesign", 
    "Mustermacher": "Dessinateur", 
    "Papiermacher": "Papiertechnologe", 
    "Sozialtherapeut": "Sozialtherapie", 
    "Glasschleifer": "Glasschleiferei", 
    "Kardiotechniker": "Herz-Lungen-Maschine", 
    "Musikp\u00e4dagoge": "Musikp\u00e4dagogik", 
    "Sportarzt": "Sportmedizin", 
    "Schachtmeister": "Polier", 
    "Landwirtschaftsmeister": "Landwirt", 
    "Programmierer": "Softwareentwickler", 
    "Logistiker": "Logistikdienstleister", 
    "Di\u00e4tberater": "Ern\u00e4hrungsberatung", 
    "Volkskundler": "volkskunde", 
    "Forstwirtschaftsmeister": "Forstfacharbeiter", 
    "Gemmologe": "Gemmologie", 
    "B\u00fchnenbildner": "B\u00fchnenbild", 
    "Familientherapeut": "Familientherapie", 
    "Molekularbiologe": "Molekularbiologie", 
    "Verkehrsflugzeugf\u00fchrer": "Pilot", 
    "Verpackungsmittelhersteller": "Verpackung", 
    "Fahrstuhlf\u00fchrer": "Aufzugf\u00fchrer", 
    "Raumplaner": "Raumplanung", 
    "Kosmetiker": "Kosmetik", 
    "Systemanalytiker": "Systemanalyse", 
    "Wirtschaftsgeograph": "Wirtschaftsgeographie", 
    "Kunsth\u00e4ndler": "Kunsthandel", 
    "Kunststofftechniker": "Verfahrensmechaniker f\u00fcr Kunststoff- und Kautschuktechnik", 
    "Revierf\u00f6rster": "F\u00f6rster", 
    "Arabist": "Arabistik", 
    "Bioinformatiker": "Bioinformatik", 
    "Medieninformatiker": "Medieninformatik", 
    "Biochemiker": "Biochemie", 
    "Baumaler": "Maler und Lackierer", 
    "Sportwissenschaftler": "Sportwissenschaft", 
    "Justizangestellter": "Justizfachangestellter", 
    "Damenma\u00dfschneider": "Ma\u00dfschneider", 
    "Chemieingenieur": "Chemieingenieurwesen", 
    "Schaufenstergestalter": "Schauwerbegestalter", 
    "Informations- und Telekommunikationssystem-Elektroniker": "IT-Systemelektroniker", 
    "Wirtschaftsingenieur": "Wirtschaftsingenieurwesen", 
    "Sozialwissenschaftler": "Sozialwissenschaften", 
    "Abf\u00fcller": "Kontraktpacker", 
    "Wirtschaftsinformatiker": "Wirtschaftsinformatik", 
    "Kraftfahrzeugf\u00fchrer": "Kraftfahrer", 
    "Religionswissenschaftler": "Religionswissenschaft", 
    "Modellbauer": "Modellbau", 
    "Sinologe": "Sinologie", 
    "Medizinischer Fu\u00dfpfleger": "Podologie", 
    "Fernmeldeinstallateur": "Fernmeldehandwerker", 
    "Kfz-Mechaniker": "Kfz-Mechatroniker", 
    "Schiffskoch": "Smut", 
    "Meinungsforscher": "Meinungsforschung", 
    "Arch\u00e4ologe": "Arch\u00e4ologie", 
    "Kunstp\u00e4dagoge": "Kunstp\u00e4dagogik", 
    "Anlageberater": "Anlageberatung", 
    "Florist": "Floristik", 
    "Maschinensetzer": "Schriftsetzer", 
    "Fahrsteiger": "Steiger (Bergbau)", 
    "Fotolithograf": "Fotolithografie", 
    "Volont\u00e4r": "Volontariat", 
    "Ozeanograph": "Meereskunde", 
    "Produktionsmechaniker": "Mechaniker", 
    "Zeichner": "Zeichnung (Kunst)", 
    "Wahrsager": "Wahrsagen", 
    "Musikwissenschaftler": "Musikwissenschaft", 
    "Kinderg\u00e4rtner": "Erzieher", 
    "Kommunikationswissenschaftler": "Kommunikationswissenschaft", 
    "Apothekenhelfer": "Pharmazeutisch-kaufm\u00e4nnischer Angestellter", 
    "Handsetzer": "Schriftsetzer", 
    "Checkkapit\u00e4n": "Pilot", 
    "Gestalter": "Designer", 
    "Heilerziehungspfleger": "Heilerziehungspflege", 
    "Fernsehmoderator": "Moderator (Beruf)", 
    "Forstingenieur": "F\u00f6rster", 
    "Automechaniker": "Kfz-Mechatroniker", 
    "Fotodesigner": "Designer", 
    "Zentralheizungs- und L\u00fcftungsbauer": "Heizungsbauer", 
    "Messtechniker": "Prozessleitelektroniker", 
    "Lokomotivf\u00fchrer": "Triebfahrzeugf\u00fchrer", 
    "Berufsflugzeugf\u00fchrer": "Commercial Pilot Licence", 
    "Literaturwissenschaftler": "Literaturwissenschaft", 
    "Schulpsychologe": "Schulpsychologie", 
    "Maler": "Malerei", 
    "Niederlandist": "Niederlandistik", 
    "Anthropologe": "Anthropologie", 
    "Gamedesigner": "Game Designer", 
    "Zahnarzthelfer": "Zahnmedizinischer Fachangestellter", 
    "Rohrvorrichter": "Vorrichten (Schwei\u00dftechnik)", 
    "Handelsfachpacker": "Fachlagerist", 
    "Reproretuscheur": "Retusche", 
    "Chemiefacharbeiter": "Chemikant", 
    "Choreograph": "Choreografie", 
    "Glockengie\u00dfer": "Metall- und Glockengie\u00dfer", 
    "Berufsp\u00e4dagoge": "Gepr\u00fcfter Berufsp\u00e4dagoge", 
    "K\u00fcchendirektor": "K\u00fcchenchef", 
    "Blumenbinder": "Floristik (Handwerk)", 
    "Blechlocher": "Locheisen", 
    "Hauswart": "Hausmeister", 
    "Parodist": "Parodie", 
    "Glasreiniger": "Fensterreinigungsmittel", 
    "Krabbenfischer": "Krabbenfischerei", 
    "Afrikanist": "Afrikanistik im deutschen Sprachraum", 
    "Uhrenrestaurator": "Uhrmacher", 
    "\u00d6konometriker": "\u00d6konometrie", 
    "General Manager": "Generaldirektor", 
    "Notarfachangestellter": "Rechtsanwalts- und Notarfachangestellter", 
    "Berufsj\u00e4ger": "Revierj\u00e4ger", 
    "Wirtschaftsethiker": "Wirtschaftsethik", 
    "Lackierer": "Maler und Lackierer", 
    "Versicherungskaufmann": "Kaufmann f\u00fcr Versicherungen und Finanzen", 
    "Sprengmeister": "Sprengberechtigter", 
    "Judaist": "Judaistik", 
    "Hafenfacharbeiter": "Hafenarbeiter", 
    "Stahlbauschlosser": "Schlosserei", 
    "Bildhauer": "Bildhauerei", 
    "Verwaltungsjurist": "Verwaltungsrecht", 
    "Sozialp\u00e4dagogischer Assistent": "Sozialp\u00e4dagogische Assistenz", 
    "Buchgestalter": "Buchgestaltung", 
    "Wagner": "Richard Wagner", 
    "Biomathematiker": "Theoretische Biologie", 
    "Evangelischer Theologe": "Evangelische Theologie", 
    "Medizinischer Bademeister": "Masseur und medizinischer Bademeister", 
    "Kulturmanager": "Kulturmanagement", 
    "Vulkaniseur": "Vulkanisation", 
    "Hygieneinspektor": "Hygienekontrolleur", 
    "Hypnotiseur": "Hypnose", 
    "Lerntherapeut": "Lerntherapie", 
    "Glasmaler": "Glasmalerei", 
    "Verwaltungswissenschaftler": "Verwaltungswissenschaft", 
    "Kunststoffverarbeiter": "Verfahrensmechaniker f\u00fcr Kunststoff- und Kautschuktechnik", 
    "Diskjockey": "DJ", 
    "Waldarbeiter": "Forstwirt", 
    "Haush\u00e4lter": "Haush\u00e4lterin", 
    "Kleinpflasterleger": "Pflasterer", 
    "Gleichstellungsbeauftragter": "Gleichstellungsbeauftragte", 
    "B\u00fchnent\u00e4nzer": "B\u00fchnentanz", 
    "Kunstmaler": "Malerei", 
    "Betriebs\u00f6konom": "Betriebswirt", 
    "Toxikologe": "Toxikologie", 
    "Musiklehrer": "Musikp\u00e4dagogik", 
    "Pal\u00e4ontologe": "Pal\u00e4ontologie", 
    "Hilfspolizist": "Hilfspolizei", 
    "Bandweber": "Bandweberei", 
    "Organisationsprogrammierer": "Anwendungsprogrammierer", 
    "Biophysiker": "Biophysik", 
    "Aufbereiter": "Konditionierer", 
    "Mediaplaner": "Mediaplanung", 
    "Meeresbiologe": "Meeresbiologie", 
    "Werkstattmeister": "Funktionsmeistersystem", 
    "Holzschleifer": "Holzstoff", 
    "Lichtplaner": "Lichtplanung", 
    "Altertumswissenschaftler": "Altertumsforscher", 
    "Barmixer": "Barkeeper", 
    "Sch\u00e4dlingsbek\u00e4mpfer": "Kammerj\u00e4ger", 
    "Diplom-Pharmazeut": "Pharmazeut", 
    "Entbindungspfleger": "Hebamme", 
    "Sonderp\u00e4dagoge": "Sonderp\u00e4dagogik", 
    "Handformer": "Handformerei", 
    "Hauswirtschafter": "Hauswirtschaft", 
    "Beschlie\u00dfer": "Beschlie\u00dferin", 
    "Agrotechniker": "Landtechnik", 
    "Ver- und Entsorger": "Fachkraft f\u00fcr Kreislauf- und Abfallwirtschaft", 
    "Bausteinmetz": "Steinmetz", 
    "Wissenschaftshistoriker": "Wissenschaftsgeschichte", 
    "Bezirksnotar": "Amtsnotar", 
    "Kunsthandwerker": "Kunsthandwerk", 
    "Holzbildhauer": "Bildschnitzer", 
    "Sous-Chef": "K\u00fcchenchef", 
    "Grafikdesigner": "Grafikdesign", 
    "Anrei\u00dfer": "Teaser", 
    "Politologe": "Politikwissenschaft", 
    "Werbekaufmann": "Kaufmann f\u00fcr Marketingkommunikation", 
    "Destillateur": "Destillation", 
    "Berufssportler": "Profisport", 
    "B\u00f6rsenh\u00e4ndler": "B\u00f6rsenmakler", 
    "Streetworker": "Streetwork", 
    "Geowissenschaftler": "Geowissenschaften", 
    "Musikinstrumentenbauer": "Musikinstrumentenbau", 
    "Agraringenieur": "Agrarwissenschaften", 
    "Industriekletterer": "Industrieklettern", 
    "Linguist": "Sprachwissenschaft", 
    "Repassierer": "Laufmasche", 
    "Druckvorlagenhersteller": "Mediengestalter_Digital_und_Print", 
    "Supervisor": "Supervision", 
    "Ethnograph": "Ethnographie", 
    "Fachkrankenpfleger": "Fachgesundheits- und Krankenpfleger", 
    "Projektingenieur": "Ingenieur", 
    "Ziseleur": "Ziselieren", 
    "Schwei\u00dffachingenieur": "Schwei\u00dfaufsicht", 
    "Planierer": "Grader", 
    "M\u00f6nch": "M\u00f6nchtum", 
    "Brennschneider": "Autogenes Brennschneiden", 
    "Phonetiker": "Phonetik", 
    "Theaterwissenschaftler": "Theaterwissenschaft", 
    "Forstmeister": "Oberf\u00f6rster", 
    "Bilanzbuchhalter": "Buchhalter", 
    "Rechtsanwaltsgehilfe": "Rechtsanwaltsfachangestellter", 
    "B\u00fcrogehilfe": "Sekret\u00e4r", 
    "Versteigerer": "Auktion", 
    "Zugbegleiter": "Schaffner (Beruf)", 
    "Personensch\u00fctzer": "Personenschutz", 
    "Geophysiker": "Geophysik", 
    "Iranist": "Iranistik", 
    "Metallograph": "Metallograf", 
    "Steindrucker": "Lithografie", 
    "Pflanzenarzt": "Phytomediziner", 
    "Landschaftsg\u00e4rtner": "Garten- und Landschaftsbau", 
    "Kopierer": "Elektrofotografie", 
    "Hochseefischer": "Hochseefischerei", 
    "Bildgie\u00dfer": "Bildgie\u00dferei", 
    "Fitnesstrainer": "Fitnesstraining", 
    "Servierer": "Kellner", 
    "Patentanwalt": "Patentanwalt (Deutschland)", 
    "Chors\u00e4nger": "Chor (Musik)", 
    "Textildesigner": "Textildesign", 
    "Sprachforscher": "Sprachwissenschaft", 
    "Kunsttherapeut": "Kunsttherapie", 
    "Tankwart": "Tankstelle", 
    "Schwarzstra\u00dfenbauer": "Asphaltbauer", 
    "Sicherheitsingenieur": "Fachkraft f\u00fcr Arbeitssicherheit", 
    "Arbitrageur": "Arbitrage", 
    "Mess- und Regelmechaniker": "Prozessleitelektroniker", 
    "Kommunikationsdesigner": "Grafikdesign", 
    "Gesangslehrer": "Gesangsp\u00e4dagogik", 
    "Analytiker": "Analyst", 
    "Gastronom": "Gastwirt", 
    "Holzr\u00fccker": "Holzr\u00fccken", 
    "Hippotherapeut": "Hippotherapie", 
    "Automobilmechaniker": "Kfz-Mechatroniker", 
    "Theaterplastiker": "B\u00fchnenmaler", 
    "Modelltischler": "Tischler", 
    "Herrenma\u00dfschneider": "Ma\u00dfschneider", 
    "Systemverwalter": "Systemadministrator", 
    "Bordmechaniker": "Flugingenieur", 
    "Einzelhandelskaufmann": "Kaufmann im Einzelhandel", 
    "Innenarchitekt": "Innenarchitektur", 
    "Kunstschlosser": "Kunstschmied", 
    "Astrologe": "Astrologie", 
    "Stomatherapeut": "Enterostomatherapie", 
    "Informationstechnikermeister": "Informationstechniker", 
    "Arbeitstherapeut": "Arbeitserzieher", 
    "Wertpapierh\u00e4ndler": "Broker", 
    "Karikaturist": "Karikatur", 
    "Hobler": "Uwe Hobler", 
    "Qualit\u00e4tspr\u00fcfer": "Qualit\u00e4tsfachmann", 
    "Hundefriseur": "Hundefris\u00f6r", 
    "Busfahrer": "Berufskraftfahrer", 
    "Polsterer": "Polstern", 
    "Masseur": "Masseur und medizinischer Bademeister", 
    "Tiefbohrer": "Bohrer", 
    "Verpackungstechniker": "Verpackungsmittelmechaniker", 
    "Medienkaufmann": "Medienkaufmann Digital und Print", 
    "Fu\u00dfballspieler": "Fu\u00dfball", 
    "Sozialpsychologe": "Sozialpsychologie", 
    "Geb\u00e4rdensprachdolmetscher": "Geb\u00e4rdensprache", 
    "Medienmanager": "Medienmanagement", 
    "Gesundheits- und Kinderkrankenpfleger": "Kinderkrankenpflege", 
    "Kommissionierer": "Kommissionierung", 
    "Buchpr\u00fcfer": "Wirtschaftspr\u00fcfer", 
    "Gerontologe": "Gerontologie", 
    "Turkologe": "Turkologie", 
    "Friedhofsg\u00e4rtner": "G\u00e4rtner", 
    "Vermessungsgehilfe": "Messgehilfe", 
    "Eisengie\u00dfer": "Gie\u00dfen (Verfahren)", 
    "Filialleiter": "Filiale", 
    "Industriedesigner": "Produktdesign", 
    "Gebrauchswerber": "Schauwerbegestalter", 
    "Gas- und Wasserinstallateur": "Installateur", 
    "Tierarzthelfer": "Tiermedizinischer Fachangestellter", 
    "Telekommunikationselektroniker": "Kommunikationselektroniker", 
    "Kinderkrankenpfleger": "Kinderkrankenpflege", 
    "Semitist": "Semitistik", 
    "Literatur\u00fcbersetzer": "\u00dcbersetzer", 
    "Tierpsychologe": "Tierpsychologie", 
    "Tanzp\u00e4dagoge": "Tanz", 
    "Statiker": "Tragwerksplaner", 
    "Jugendpfleger": "Kinder- und Jugendhilfe", 
    "B\u00fcrsten- und Pinselmacher": "B\u00fcrstenbinder", 
    "Imkermeister": "Imker", 
    "Hufbeschlagschmied": "Hufschmied", 
    "\u00d6kotrophologe": "\u00d6kotrophologie", 
    "Motologe": "Motologie", 
    "Informations-Broker": "Informationsvermittler", 
    "Verkehrsingenieur": "Verkehrsplaner", 
    "Schwimmmeistergehilfe": "Fachangestellter f\u00fcr B\u00e4derbetriebe", 
    "Mikrobiologe": "Mikrobiologie", 
    "Hausangestellter": "Hauspersonal", 
    "Betonbauer": "Beton- und Stahlbetonbauer", 
    "Auslandskorrespondent": "Korrespondent", 
    "Feinmechaniker": "Feinmechanik", 
    "Sprachwissenschaftler": "Sprachwissenschaft", 
    "Podologe": "Podologie", 
    "Hilfsarbeiter": "Hilfsarbeitskraft", 
    "Logop\u00e4de": "Logop\u00e4die", 
    "Sicherheitstechniker": "Fachkraft f\u00fcr Arbeitssicherheit", 
    "Notargehilfe": "Rechtsanwalts- und Notarfachangestellter", 
    "Anglist": "Anglistik", 
    "Orthop\u00e4dieschuhmacher": "Orthop\u00e4dieschuhtechniker", 
    "medizinischer Bademeister": "Masseur und medizinischer Bademeister", 
    "Denkmalpfleger": "Denkmalpflege", 
    "Ergotherapeut": "Ergotherapie", 
    "Fotografiker": "Grafiker", 
    "Chefkoch": "K\u00fcchenchef", 
    "Hydrologe": "Hydrologie", 
    "Werkzeugschleifer": "Schneidwerkzeugmechaniker", 
    "Latinist": "Latinistik", 
    "Theaterp\u00e4dagoge": "Theaterp\u00e4dagogik", 
    "Stauer": "Stauerei", 
    "Elektriker": "Elektroinstallateur", 
    "H\u00f6rfunkmoderator": "Moderator (Beruf)", 
    "Kamera-Assistent": "Kameraassistent", 
    "Blechschlosser": "Schlosserei", 
    "Oberkellner": "Kellner", 
    "Maschinenschlosser": "Metallbau", 
    "Patissier": "P\u00e2tissier", 
    "Medienwissenschaftler": "Medienwissenschaft", 
    "Keltologe": "Keltologie", 
    "Kontrolleur": "Schaffner (Beruf)", 
    "Orthop\u00e4diemechaniker": "Orthop\u00e4dietechnik-Mechaniker", 
    "Kabarettist": "Kabarett", 
    "Gesch\u00e4ftsf\u00fchrer": "Gesch\u00e4ftsf\u00fchrung", 
    "Musikmanager": "Musikmanagement", 
    "Bergmechaniker": "Bergbautechnologe", 
    "Speditionskaufmann": "Kaufmann f\u00fcr Spedition und Logistikdienstleistung", 
    "Politischer Berater": "Politikberatung", 
    "Bauleiter": "Bauleitung", 
    "Dorfhelfer": "Hauswirtschaft"
}